tileops-0.0.1.dev2.dist-info/licenses/LICENSE
top/__init__.py
top/kernel/__init__.py
top/kernel/bitnet.py
top/kernel/blocksparse_attention.py
top/kernel/gqa.py
top/kernel/mamba_chunk_scan.py
top/kernel/mamba_chunk_state.py
top/kernel/mha.py
top/kernel/mla.py
top/kernel/sparse_mla.py
top/kernel/linear_attention/__init__.py
top/kernel/linear_attention/linear_attn.py
top/utils/__init__.py
top/utils/utils.py
tileops-0.0.1.dev2.dist-info/METADATA
tileops-0.0.1.dev2.dist-info/WHEEL
tileops-0.0.1.dev2.dist-info/top_level.txt
tileops-0.0.1.dev2.dist-info/RECORD
