Metadata-Version: 2.4
Name: tileops
Version: 0.0.1.dev2
Summary: TileOPs kernels for efficient inference
Author: Tile-AI
License-Expression: MIT
Requires-Python: >=3.8
License-File: LICENSE
Requires-Dist: torch>=2.1.0
Requires-Dist: numpy>=1.23.5
Requires-Dist: einops>=0.6.0
Requires-Dist: Cython
Requires-Dist: tqdm>=4.62.3
Requires-Dist: typing_extensions>=4.10.0
Requires-Dist: cloudpickle
Requires-Dist: ml_dtypes
Requires-Dist: psutil
Requires-Dist: tilelang>=0.1.6.post1
Provides-Extra: dev
Requires-Dist: yapf==0.40.2; extra == "dev"
Requires-Dist: toml==0.10.2; extra == "dev"
Requires-Dist: tomli==2.0.1; extra == "dev"
Requires-Dist: ruff==0.6.5; extra == "dev"
Requires-Dist: codespell==2.3.0; extra == "dev"
Requires-Dist: clang-format==15.0.7; extra == "dev"
Dynamic: license-file
